{
  "@type": "CreativeWork",
  "name": "Seagrass Synergy: Collaborate for Global Observing and Understanding",
  "url": "https://zenodo.org/record/10972535",
  "identifier": {
    "@type": "PropertyValue",
    "description": "DOI",
    "propertyID": "https://registry.identifiers.org/registry/doi",
    "url": "https://doi.org/10.5281/zenodo.10972535",
    "value": "10.5281/zenodo.10972535"
  },
  "description": "Global Ocean Observing System webinar Presenters: &nbsp;Lina Mtwana Nordlund and Emmett Duffy Date and Time: 27 March 2024, 15:00 CET Join us in envisioning a world with comparable seagrass data across the globe. Explore the journey from the development of the Seagrass Essential Ocean Variable to the importance of standardized measurement, data availability, and the transformative impact of openly accessible seagrass data on global biodiversity indicators. Be part of the conversation as we discuss the evolving landscape of seagrass monitoring, from essential variables and open repositories to global collaborations shaping the future of seagrass research.",
  "datePublished": "2024-03-27",
  "creator": [
    {
      "@type": "Person",
      "name": "Nordlund, Lina Mtwana"
    },
    {
      "@type": "Person",
      "name": "Duffy, J. Emmett"
    }
  ],
  "license": {
    "id": "cc-by-4.0"
  },
  "funding": [
    {
      "@type": "MonetaryGrant",
      "name": "BioEcoOcean (Horizon Europe)",
      "identifier": "101136748",
      "funder": {
        "@type": "FundingAgency",
        "name": "European Commission",
        "legalName": "European Commission",
        "url": "https://commission.europa.eu/index_en"
      }
    }
  ],
  "@context": "https://schema.org/",
  "@id": "https://raw.githubusercontent.com/BioEcoOcean/data-prov/refs/heads/main/jsonFiles/zenodo/seagrass-synergy-collaborate-for-global-observing-and-understanding-10972535.json"
}